{
  "bookings": [
    {
      "id": "3",
      "name": "princeeeeeeeeeeeeeeeeee",
      "source": "chennai",
      "destination": "dubai",
      "date": "2024-11-28"
    },
    {
      "id": "306a",
      "name": "Russhikesh",
      "source": "delhi",
      "destination": "mumbai",
      "date": "2024-03-13"
    },
    {
      "id": "1",
      "name": "sam",
      "source": "pune",
      "destination": "banglore",
      "date": "27/08/2023"
    },
    {
      "id": "8190",
      "name": "",
      "source": "",
      "destination": "",
      "date": ""
    },
    {
      "id": "1",
      "name": "Ram",
      "source": "pune",
      "destination": "nagpur",
      "date": "2024-03-12"
    },
    {
      "id": "1",
      "name": "sam",
      "source": "pune",
      "destination": "banglore",
      "date": "2024-03-05"
    },
    {
      "id": "1",
      "name": "samiksha",
      "source": "pune",
      "destination": "banglore",
      "date": "2024-03-13"
    },
    {
      "id": "8091",
      "name": "",
      "source": "",
      "destination": "",
      "date": ""
    },
    {
      "id": "ed95",
      "name": "",
      "source": "",
      "destination": "",
      "date": ""
    },
    {
      "id": "ce89",
      "name": "",
      "source": "",
      "destination": "",
      "date": ""
    },
    {
      "id": "6d10",
      "name": "",
      "source": "",
      "destination": "",
      "date": ""
    },
    {
      "id": "d0e3",
      "name": "gffff",
      "source": "",
      "destination": "",
      "date": ""
    }
  ]
}